predict_sdk/__init__.py
predict_sdk/constants.py
predict_sdk/errors.py
predict_sdk/logger.py
predict_sdk/order_builder.py
predict_sdk/py.typed
predict_sdk/types.py
predict_sdk/_internal/__init__.py
predict_sdk/_internal/contracts.py
predict_sdk/_internal/utils.py
predict_sdk/abis/CTFExchange.json
predict_sdk/abis/ConditionalTokens.json
predict_sdk/abis/ECDSAValidator.json
predict_sdk/abis/ERC20.json
predict_sdk/abis/Kernel.json
predict_sdk/abis/NegRiskAdapter.json
predict_sdk/abis/NegRiskCtfExchange.json
predict_sdk/abis/YieldBearingConditionalTokens.json
predict_sdk/abis/__init__.py
predict_sdk-0.0.12.dist-info/METADATA
predict_sdk-0.0.12.dist-info/WHEEL
predict_sdk-0.0.12.dist-info/licenses/LICENSE
predict_sdk-0.0.12.dist-info/RECORD
