Metadata-Version: 2.4
Name: predict_sdk
Version: 0.0.12
Summary: A Python SDK to help developers interface with the Predict.fun protocol
Project-URL: Homepage, https://predict.fun/
Project-URL: Documentation, https://docs.predict.fun/developers
Project-URL: Repository, https://github.com/prd-fun/predict-sdk-py
Project-URL: Issues, https://github.com/prd-fun/predict-sdk-py/issues
License-Expression: MIT
License-File: LICENSE
Requires-Python: >=3.10
Requires-Dist: eth-abi>=5.0.0
Requires-Dist: eth-account>=0.11.0
Requires-Dist: eth-typing>=4.0.0
Requires-Dist: web3<8.0.0,>=6.0.0
Provides-Extra: dev
Requires-Dist: hypothesis>=6.0.0; extra == 'dev'
Requires-Dist: mypy>=1.0.0; extra == 'dev'
Requires-Dist: pytest-asyncio>=0.21.0; extra == 'dev'
Requires-Dist: pytest-cov>=4.0.0; extra == 'dev'
Requires-Dist: pytest>=7.0.0; extra == 'dev'
Requires-Dist: ruff>=0.1.0; extra == 'dev'
